CHANGES.rst
COPYING.txt
MANIFEST.in
README.rst
setup.py
moo/__init__.py
moo/connector.py
moo/database.py
moo/ssh.py
moo/examples/freespace.sh
moo/examples/hostname.sql
moo/examples/oracle.moo
moo/examples/ssh.moo
python_moo.egg-info/PKG-INFO
python_moo.egg-info/SOURCES.txt
python_moo.egg-info/dependency_links.txt
python_moo.egg-info/top_level.txt