Metadata-Version: 1.1
Name: python-moo
Version: 0.3
Summary: Easy way how to run the same query in multiple SQL databases
Home-page: https://github.com/idxxx23/moo
Author: GNU Knight
Author-email: idxxx23@gmail.com
License: UNKNOWN
Platform: UNKNOWN
Classifier: Programming Language :: Python :: 3
Classifier: Programming Language :: Python
Classifier: License :: OSI Approved :: GNU General Public License v3 or later (GPLv3+)
Classifier: Operating System :: OS Independent
Classifier: Development Status :: 5 - Production/Stable
Classifier: Intended Audience :: Developers
Classifier: Intended Audience :: System Administrators
Classifier: Topic :: Database
Classifier: Topic :: Software Development
Classifier: Topic :: System
